orange_system_dynamics-1.1.1-py3.8-nspkg.pth
orangecontrib/system_dynamics/__init__.py
orangecontrib/system_dynamics/_version.py
orangecontrib/system_dynamics/widgets/DTDL.py
orangecontrib/system_dynamics/widgets/__init__.py
orangecontrib/system_dynamics/widgets/agent.py
orangecontrib/system_dynamics/widgets/azure.py
orangecontrib/system_dynamics/widgets/environment.py
orangecontrib/system_dynamics/widgets/geolocalization.py
orangecontrib/system_dynamics/widgets/load_simulation.py
orangecontrib/system_dynamics/widgets/name_table.py
orangecontrib/system_dynamics/widgets/service_table.py
orangecontrib/system_dynamics/widgets/simulation.py
orangecontrib/system_dynamics/widgets/statemachine.py
orangecontrib/system_dynamics/widgets/twin.py
orangecontrib/system_dynamics/widgets/icons/DTDL.svg
orangecontrib/system_dynamics/widgets/icons/agent.svg
orangecontrib/system_dynamics/widgets/icons/azure.svg
orangecontrib/system_dynamics/widgets/icons/category.svg
orangecontrib/system_dynamics/widgets/icons/environment.svg
orangecontrib/system_dynamics/widgets/icons/geolocation.svg
orangecontrib/system_dynamics/widgets/icons/load_simulation.svg
orangecontrib/system_dynamics/widgets/icons/name.svg
orangecontrib/system_dynamics/widgets/icons/service.svg
orangecontrib/system_dynamics/widgets/icons/statemachine.svg
orangecontrib/system_dynamics/widgets/icons/twin.svg
orange_system_dynamics-1.1.1.dist-info/METADATA
orange_system_dynamics-1.1.1.dist-info/WHEEL
orange_system_dynamics-1.1.1.dist-info/entry_points.txt
orange_system_dynamics-1.1.1.dist-info/namespace_packages.txt
orange_system_dynamics-1.1.1.dist-info/top_level.txt
orange_system_dynamics-1.1.1.dist-info/RECORD
