Metadata-Version: 2.1
Name: orange-system-dynamics
Version: 1.1.1
Summary: Add-on containing widgets for system dynamics operations
Home-page: https://gitlab.com/drb-python/samples/odm/sd_addon
Author: GAEL Systems
Author-email: drb-python@gael.fr
License: LGPLv3
Classifier: Programming Language :: Python :: 3.8
Classifier: Environment :: Plugins
Classifier: License :: OSI Approved :: GNU Lesser General Public License v3 (LGPLv3)
Requires-Python: >=3.8
Requires-Dist: pysd (>=3.9.0)
Requires-Dist: numpy (>=1.24)
Requires-Dist: netcdf4 (>=1.6.2)
Requires-Dist: drb-driver-eurostat (>=1.1.0)
Requires-Dist: drb-driver-file (>=1.1.0)
Requires-Dist: drb-driver-json (>=1.1.0)
Requires-Dist: drb-driver-era5 (>=1.1.0)
Requires-Dist: drb-driver-discodata (>=1.1.0)
Requires-Dist: pyshp (>=2.3.1)
Requires-Dist: pandas (>=1.5.3)
Requires-Dist: sismic (>=1.6.3)
Requires-Dist: plantuml (>=0.3.0)
Requires-Dist: agentpy (>=0.1.5)
Requires-Dist: networkx (>=3.0)
Requires-Dist: PyYAML (>=6.0)
Requires-Dist: azure-core (>=1.26.0)
Requires-Dist: azure-digitaltwins-core (>=1.2.0)
Requires-Dist: azure-identity (>=1.12.0)
Requires-Dist: configparser (>=2.4.0.0)
